LICENSE
MANIFEST.in
NOTICE
README.md
requirements.txt
setup.py
pedemath/__init__.py
pedemath/matrix.py
pedemath/quat.py
pedemath/rect.py
pedemath/rect3.py
pedemath/vec2.py
pedemath/vec3.py
pedemath.egg-info/PKG-INFO
pedemath.egg-info/SOURCES.txt
pedemath.egg-info/dependency_links.txt
pedemath.egg-info/top_level.txt