Metadata-Version: 1.1
Name: pedemath
Version: 0.0.6
Summary: Pedemath is a Python Vector and Math library
Home-page: http://github.com/olsoneric/pedemath
Author: Eric Olson
Author-email: me@olsoneric.com
License: Apache 2.0
Keywords: vector,math,matrix,quaternion
Platform: UNKNOWN
Classifier: Development Status :: 2 - Pre-Alpha
Classifier: License :: OSI Approved :: Apache Software License
Classifier: Programming Language :: Python
Classifier: Programming Language :: Python :: 2.7
